diffusion/__init__.py
diffusion/sampling.py
diffusion/utils.py
diffusion/models/__init__.py
diffusion/models/cc12m_1.py
diffusion/models/danbooru_128.py
diffusion/models/imagenet_128.py
diffusion/models/models.py
diffusion/models/wikiart_128.py
diffusion/models/wikiart_256.py
diffusion/models/yfcc_1.py
diffusion/models/yfcc_2.py
v_diffusion_pytorch-0.0.2.dist-info/LICENSE
v_diffusion_pytorch-0.0.2.dist-info/METADATA
v_diffusion_pytorch-0.0.2.dist-info/WHEEL
v_diffusion_pytorch-0.0.2.dist-info/top_level.txt
v_diffusion_pytorch-0.0.2.dist-info/RECORD
