Metadata-Version: 2.1
Name: v-diffusion-pytorch
Version: 0.0.2
Summary: v objective diffusion inference code for PyTorch.
Home-page: https://github.com/crowsonkb/v-diffusion-pytorch
Author: Katherine Crowson
Author-email: crowsonkb@gmail.com
License: MIT
Platform: UNKNOWN
